odoo8_addon_sale_exception_nostock-8.0.1.2.0.99.dev12-py3.8-nspkg.pth
odoo_addons/sale_exception_nostock/__init__.py
odoo_addons/sale_exception_nostock/__openerp__.py
odoo_addons/sale_exception_nostock/data/data.xml
odoo_addons/sale_exception_nostock/i18n/ca.po
odoo_addons/sale_exception_nostock/i18n/de.po
odoo_addons/sale_exception_nostock/i18n/es.po
odoo_addons/sale_exception_nostock/i18n/fr.po
odoo_addons/sale_exception_nostock/i18n/it.po
odoo_addons/sale_exception_nostock/i18n/nl_NL.po
odoo_addons/sale_exception_nostock/i18n/pt_BR.po
odoo_addons/sale_exception_nostock/i18n/ro.po
odoo_addons/sale_exception_nostock/i18n/sale_exception_nostock.pot
odoo_addons/sale_exception_nostock/i18n/sk.po
odoo_addons/sale_exception_nostock/i18n/sl.po
odoo_addons/sale_exception_nostock/i18n/tr.po
odoo_addons/sale_exception_nostock/i18n/tr_TR.po
odoo_addons/sale_exception_nostock/model/__init__.py
odoo_addons/sale_exception_nostock/model/sale.py
odoo_addons/sale_exception_nostock/static/description/icon.png
odoo_addons/sale_exception_nostock/test/__init__.py
odoo_addons/sale_exception_nostock/test/no_stock_test.yml
odoo_addons/sale_exception_nostock/test/test_utils.py
odoo_addons/sale_exception_nostock/tests/__init__.py
odoo_addons/sale_exception_nostock/tests/test_dropshipping_skip_check.py
odoo8_addon_sale_exception_nostock-8.0.1.2.0.99.dev12.dist-info/METADATA
odoo8_addon_sale_exception_nostock-8.0.1.2.0.99.dev12.dist-info/WHEEL
odoo8_addon_sale_exception_nostock-8.0.1.2.0.99.dev12.dist-info/namespace_packages.txt
odoo8_addon_sale_exception_nostock-8.0.1.2.0.99.dev12.dist-info/top_level.txt
odoo8_addon_sale_exception_nostock-8.0.1.2.0.99.dev12.dist-info/RECORD
