Metadata-Version: 2.1
Name: odoo8-addon-sale-exception-nostock
Version: 8.0.1.2.0.99.dev12
Summary: Sale stock exception
Home-page: http://www.camptocamp.com
Author: Camptocamp,Odoo Community Association (OCA)
Author-email: support@odoo-community.org
License: AGPL-3
Platform: UNKNOWN
Classifier: Programming Language :: Python
Classifier: Framework :: Odoo
Classifier: Framework :: Odoo :: 8.0
Classifier: License :: OSI Approved :: GNU Affero General Public License v3
Requires-Python: ~=2.7
Requires-Dist: odoo8-addon-sale-exceptions
Requires-Dist: odoo (<9.0a,>=8.0a)
